replcraft/__init__.py
replcraft/main.py
replcraft_rexum-1.5.1.dist-info/LICENSE
replcraft_rexum-1.5.1.dist-info/METADATA
replcraft_rexum-1.5.1.dist-info/WHEEL
replcraft_rexum-1.5.1.dist-info/top_level.txt
replcraft_rexum-1.5.1.dist-info/RECORD
