Metadata-Version: 2.1
Name: replcraft-rexum
Version: 1.5.1
Summary: ReplCraft implementation in Python
Home-page: https://git.rexum.space/rexum/replcraft-py
Author: rexum
Author-email: lyamt23pk@mozmail.com
Project-URL: Bug Tracker, https://git.rexum.space/rexum/replcraft-py/issues
Classifier: Programming Language :: Python :: 3
Classifier: License :: OSI Approved :: MIT License
Classifier: Operating System :: OS Independent
Requires-Python: >=3.8
License-File: LICENSE
